my_model/VERSION
my_model/__init__.py
my_model/config.yml
my_model/pipeline.py
my_model/predict.py
my_model/pysetup.py
my_model/testtt.py
my_model/train_pipeline.py
my_model/config/__init__.py
my_model/config/core.py
my_model/datasets/__init__.py
my_model/datasets/test.csv
my_model/datasets/train.csv
my_model/processing/__init__.py
my_model/processing/data_manager.py
my_model/processing/validation.py
my_model/trained_models/__init__.py
my_model/trained_models/genero_pipe_m1.0.pkl
modelo_4-1.0.dist-info/METADATA
modelo_4-1.0.dist-info/WHEEL
modelo_4-1.0.dist-info/top_level.txt
modelo_4-1.0.dist-info/RECORD
