Metadata-Version: 2.1
Name: modelo-4
Version: 1.0
Summary: Example model package.
Author: code125443
Author-email: miguelch467@yahoo.es
Requires-Python: >=3.6.0
Requires-Dist: numpy (<=1.23.4)
Requires-Dist: pandas (<=1.5.1)
Requires-Dist: pydantic (<=1.10.2)
Requires-Dist: scikit-learn (<=1.1.3)
Requires-Dist: strictyaml (<=1.6.2)
Requires-Dist: ruamel.yaml (<=0.17.21)
Requires-Dist: feature-engine (<=1.5.1)
Requires-Dist: joblib (<=1.2.0)
